nemotron_graphic_elements_v1/__init__.py
nemotron_graphic_elements_v1/config.json
nemotron_graphic_elements_v1/graphic_element_v1.py
nemotron_graphic_elements_v1/model.py
nemotron_graphic_elements_v1/utils.py
nemotron_graphic_elements_v1/weights.py
nemotron_graphic_elements_v1/post_processing/graphic_elt_pp.py
nemotron_graphic_elements_v1/yolox/__init__.py
nemotron_graphic_elements_v1/yolox/boxes.py
nemotron_graphic_elements_v1/yolox/darknet.py
nemotron_graphic_elements_v1/yolox/network_blocks.py
nemotron_graphic_elements_v1/yolox/yolo_fpn.py
nemotron_graphic_elements_v1/yolox/yolo_head.py
nemotron_graphic_elements_v1/yolox/yolo_pafpn.py
nemotron_graphic_elements_v1/yolox/yolox.py
nemotron_graphic_elements_v1-1.0.0.dist-info/METADATA
nemotron_graphic_elements_v1-1.0.0.dist-info/WHEEL
nemotron_graphic_elements_v1-1.0.0.dist-info/top_level.txt
nemotron_graphic_elements_v1-1.0.0.dist-info/RECORD
