Metadata-Version: 2.4
Name: nemotron-graphic-elements-v1
Version: 1.0.0
Summary: NVIDIA Nemotron Graphic Elements v1 - A specialized object detection system for identifying and extracting key elements from charts and graphs
Author-email: NVIDIA Corporation <tviel@nvidia.com>
License: NVIDIA Open Model License
Project-URL: Homepage, https://huggingface.co/nvidia/nemotron-graphic-elements-v1
Project-URL: Documentation, https://huggingface.co/nvidia/nemotron-graphic-elements-v1
Project-URL: Repository, https://huggingface.co/nvidia/nemotron-graphic-elements-v1
Project-URL: Bug Reports, https://app.intigriti.com/programs/nvidia/nvidiavdp/detail
Keywords: object-detection,yolox,charts,graphics,pdf-ingestion,computer-vision
Classifier: Development Status :: 5 - Production/Stable
Classifier: Intended Audience :: Developers
Classifier: Intended Audience :: Science/Research
Classifier: Topic :: Scientific/Engineering :: Artificial Intelligence
Classifier: Topic :: Scientific/Engineering :: Image Recognition
Classifier: Programming Language :: Python :: 3
Classifier: Programming Language :: Python :: 3.8
Classifier: Programming Language :: Python :: 3.9
Classifier: Programming Language :: Python :: 3.10
Classifier: Programming Language :: Python :: 3.11
Requires-Python: >=3.8
Requires-Dist: torch>=2.0.0
Requires-Dist: numpy>=1.21.0
Requires-Dist: matplotlib>=3.5.0
Requires-Dist: pandas>=1.3.0
Requires-Dist: Pillow>=9.0.0
Requires-Dist: huggingface_hub>=0.20.0
Provides-Extra: dev
Requires-Dist: jupyter>=1.0.0; extra == "dev"
Requires-Dist: notebook>=6.4.0; extra == "dev"
